cluster_logger/__init__.py
cluster_logger/config_builder.py
cluster_logger/fluent_logger.py
cluster_logger/logger.py
cluster_logger-0.5.0.dist-info/METADATA
cluster_logger-0.5.0.dist-info/RECORD
cluster_logger-0.5.0.dist-info/WHEEL
cluster_logger-0.5.0.dist-info/top_level.txt
