Metadata-Version: 2.1
Name: cluster-logger
Version: 0.5.0
Summary: Library for wrapping cluster logging for Altamira projects.
Home-page: https://bitbucket.di2e.net/projects/PIR/repos/websl-logging
Author: Nick Gernert
Author-email: nicholas.gernert@altamiracorp.com
License: UNKNOWN
Platform: UNKNOWN
Classifier: Programming Language :: Python :: 3
Classifier: License :: OSI Approved :: MIT License
Classifier: Operating System :: OS Independent
Requires-Dist: fluent-logger
